{
  "live": "Live版",
  "name": "郑铿宏",
  "gender": "男",
  "birth": "1989-12",
  "university": "暨南大学",
  "grade": "13届本科",
  "major": "计算机科学与技术",
  "phone": "186-1712-0383",
  "email": "zhengkenghong@gmail.com",
  "gravatar": "public/images/gravatar.jpeg",
  "sns": [{
    "href": "https://twitter.com/zhengkenghong",
    "alt": "twitter",
    "src": "public/images/twitter.png"
  }, {
    "href": "http://www.zkh.im/wordpress/",
    "alt": "blog",
    "src": "public/images/wordpress.png"
  }, {
    "href": "http://chanyouji.com/trips/37829",
    "alt": "chanyouji",
    "src": "public/images/chanyouji.png"
  }, {
    "href": "http://weibo.com/zhengkenghong",
    "alt": "weibo",
    "src": "public/images/weibo.png"
  }, {
    "href": "https://github.com/ZKHelloworld",
    "alt": "github",
    "src": "public/images/github.png"
  }]
}
